sparrowrpc/__init__.py
sparrowrpc/bases.py
sparrowrpc/decorators.py
sparrowrpc/engine.py
sparrowrpc/exceptions.py
sparrowrpc/lib.py
sparrowrpc/messages.py
sparrowrpc/pyscript.py
sparrowrpc/registers.py
sparrowrpc/serialisers.py
sparrowrpc/_template_/__init__.py
sparrowrpc/_template_/transports/__init__.py
sparrowrpc/_template_/transports/websockets.py
sparrowrpc/asyncio/__init__.py
sparrowrpc/asyncio/transports/__init__.py
sparrowrpc/asyncio/transports/websockets.py
sparrowrpc/encoders/__init__.py
sparrowrpc/encoders/base.py
sparrowrpc/encoders/hs.py
sparrowrpc/encoders/v050.py
sparrowrpc/threaded/__init__.py
sparrowrpc/threaded/transports/__init__.py
sparrowrpc/threaded/transports/websockets.py
sparrowrpc-0.1.2.dist-info/METADATA
sparrowrpc-0.1.2.dist-info/WHEEL
sparrowrpc-0.1.2.dist-info/top_level.txt
sparrowrpc-0.1.2.dist-info/RECORD
