Metadata-Version: 2.4
Name: sparrowrpc
Version: 0.1.2
Summary: A Multi-Transport Peer-to-Peer bidirectional RPC System and Protocol Engine
Author-email: Rasjid Wilcox <rasjidw@openminddev.net>
License-Expression: MIT OR Apache-2.0
Classifier: Development Status :: 3 - Alpha
Requires-Python: >=3.8
Requires-Dist: binarychain
Requires-Dist: backports.strenum; python_version < "3.11"
Provides-Extra: dev
Requires-Dist: pytest; extra == "dev"
Requires-Dist: pytest-cov; extra == "dev"
Requires-Dist: pytest-asyncio; extra == "dev"
Provides-Extra: websockets
Requires-Dist: websockets; extra == "websockets"
Provides-Extra: msgpack
Requires-Dist: msgpack; extra == "msgpack"
Provides-Extra: cbor
Requires-Dist: cbor2; extra == "cbor"
